{
  "id": "731-679-N--2020-05-05--13.19.04--detections",
  "model": "ResNet50_COCO_best_v2.0.1.h5",
  "summary": {
    "total": 4,
    "car": 4
  },
  "731-679-N--2020-05-05--13.19.04--detections--1--car--26.6--12x9--208.75v220.84": {
    "type": "car",
    "id": "731-679-N--2020-05-05--13.19.04--detections--1--car--26.6--12x9--208.75v220.84",
    "percentage_probability": 26.56576633453369,
    "box_points": [
      208,
      75,
      220,
      84
    ]
  },
  "731-679-N--2020-05-05--13.19.04--detections--2--car--41.3--19x18--332.55v351.73": {
    "type": "car",
    "id": "731-679-N--2020-05-05--13.19.04--detections--2--car--41.3--19x18--332.55v351.73",
    "percentage_probability": 41.31025671958923,
    "box_points": [
      332,
      55,
      351,
      73
    ]
  },
  "731-679-N--2020-05-05--13.19.04--detections--3--car--65.6--23x22--45.107v68.129": {
    "type": "car",
    "id": "731-679-N--2020-05-05--13.19.04--detections--3--car--65.6--23x22--45.107v68.129",
    "percentage_probability": 65.5599594116211,
    "box_points": [
      45,
      107,
      68,
      129
    ]
  },
  "731-679-N--2020-05-05--13.19.04--detections--4--car--80.1--36x39--64.136v100.175": {
    "type": "car",
    "id": "731-679-N--2020-05-05--13.19.04--detections--4--car--80.1--36x39--64.136v100.175",
    "percentage_probability": 80.05854487419128,
    "box_points": [
      64,
      136,
      100,
      175
    ]
  }
}
