{
  "id": "731-679-N--2020-05-05--13.36.49--detections",
  "model": "ResNet50_COCO_best_v2.0.1.h5",
  "summary": {
    "total": 8,
    "car": 6,
    "bus": 2
  },
  "731-679-N--2020-05-05--13.36.49--detections--1--car--43.5--12x8--106.80v118.88": {
    "type": "car",
    "id": "731-679-N--2020-05-05--13.36.49--detections--1--car--43.5--12x8--106.80v118.88",
    "percentage_probability": 43.46417784690857,
    "box_points": [
      106,
      80,
      118,
      88
    ]
  },
  "731-679-N--2020-05-05--13.36.49--detections--2--car--27.7--16x11--39.95v55.106": {
    "type": "car",
    "id": "731-679-N--2020-05-05--13.36.49--detections--2--car--27.7--16x11--39.95v55.106",
    "percentage_probability": 27.672606706619263,
    "box_points": [
      39,
      95,
      55,
      106
    ]
  },
  "731-679-N--2020-05-05--13.36.49--detections--3--bus--31.2--15x18--27.78v42.96": {
    "type": "bus",
    "id": "731-679-N--2020-05-05--13.36.49--detections--3--bus--31.2--15x18--27.78v42.96",
    "percentage_probability": 31.217962503433228,
    "box_points": [
      27,
      78,
      42,
      96
    ]
  },
  "731-679-N--2020-05-05--13.36.49--detections--4--car--92.0--25x12--207.94v232.106": {
    "type": "car",
    "id": "731-679-N--2020-05-05--13.36.49--detections--4--car--92.0--25x12--207.94v232.106",
    "percentage_probability": 92.03235507011414,
    "box_points": [
      207,
      94,
      232,
      106
    ]
  },
  "731-679-N--2020-05-05--13.36.49--detections--5--car--44.9--19x18--42.104v61.122": {
    "type": "car",
    "id": "731-679-N--2020-05-05--13.36.49--detections--5--car--44.9--19x18--42.104v61.122",
    "percentage_probability": 44.914957880973816,
    "box_points": [
      42,
      104,
      61,
      122
    ]
  },
  "731-679-N--2020-05-05--13.36.49--detections--6--car--39.9--33x38--65.121v98.159": {
    "type": "car",
    "id": "731-679-N--2020-05-05--13.36.49--detections--6--car--39.9--33x38--65.121v98.159",
    "percentage_probability": 39.935725927352905,
    "box_points": [
      65,
      121,
      98,
      159
    ]
  },
  "731-679-N--2020-05-05--13.36.49--detections--7--car--92.8--48x27--198.131v246.158": {
    "type": "car",
    "id": "731-679-N--2020-05-05--13.36.49--detections--7--car--92.8--48x27--198.131v246.158",
    "percentage_probability": 92.79645681381226,
    "box_points": [
      198,
      131,
      246,
      158
    ]
  },
  "731-679-N--2020-05-05--13.36.49--detections--8--bus--29.2--34x33--64.126v98.159": {
    "type": "bus",
    "id": "731-679-N--2020-05-05--13.36.49--detections--8--bus--29.2--34x33--64.126v98.159",
    "percentage_probability": 29.217803478240967,
    "box_points": [
      64,
      126,
      98,
      159
    ]
  }
}
