{
  "id": "731-679-N--2020-05-05--13.14.25--detections",
  "model": "ResNet50_COCO_best_v2.0.1.h5",
  "summary": {
    "total": 8,
    "car": 8
  },
  "731-679-N--2020-05-05--13.14.25--detections--1--car--38.5--16x17--334.55v350.72": {
    "type": "car",
    "id": "731-679-N--2020-05-05--13.14.25--detections--1--car--38.5--16x17--334.55v350.72",
    "percentage_probability": 38.49458694458008,
    "box_points": [
      334,
      55,
      350,
      72
    ]
  },
  "731-679-N--2020-05-05--13.14.25--detections--2--car--33.5--9x6--90.74v99.80": {
    "type": "car",
    "id": "731-679-N--2020-05-05--13.14.25--detections--2--car--33.5--9x6--90.74v99.80",
    "percentage_probability": 33.50635766983032,
    "box_points": [
      90,
      74,
      99,
      80
    ]
  },
  "731-679-N--2020-05-05--13.14.25--detections--3--car--38.7--8x7--69.76v77.83": {
    "type": "car",
    "id": "731-679-N--2020-05-05--13.14.25--detections--3--car--38.7--8x7--69.76v77.83",
    "percentage_probability": 38.746801018714905,
    "box_points": [
      69,
      76,
      77,
      83
    ]
  },
  "731-679-N--2020-05-05--13.14.25--detections--4--car--52.0--10x6--108.79v118.85": {
    "type": "car",
    "id": "731-679-N--2020-05-05--13.14.25--detections--4--car--52.0--10x6--108.79v118.85",
    "percentage_probability": 51.99806094169617,
    "box_points": [
      108,
      79,
      118,
      85
    ]
  },
  "731-679-N--2020-05-05--13.14.25--detections--5--car--46.1--12x10--75.82v87.92": {
    "type": "car",
    "id": "731-679-N--2020-05-05--13.14.25--detections--5--car--46.1--12x10--75.82v87.92",
    "percentage_probability": 46.07817828655243,
    "box_points": [
      75,
      82,
      87,
      92
    ]
  },
  "731-679-N--2020-05-05--13.14.25--detections--6--car--38.4--12x10--98.83v110.93": {
    "type": "car",
    "id": "731-679-N--2020-05-05--13.14.25--detections--6--car--38.4--12x10--98.83v110.93",
    "percentage_probability": 38.449668884277344,
    "box_points": [
      98,
      83,
      110,
      93
    ]
  },
  "731-679-N--2020-05-05--13.14.25--detections--7--car--64.2--18x13--105.92v123.105": {
    "type": "car",
    "id": "731-679-N--2020-05-05--13.14.25--detections--7--car--64.2--18x13--105.92v123.105",
    "percentage_probability": 64.19586539268494,
    "box_points": [
      105,
      92,
      123,
      105
    ]
  },
  "731-679-N--2020-05-05--13.14.25--detections--8--car--53.5--35x18--215.105v250.123": {
    "type": "car",
    "id": "731-679-N--2020-05-05--13.14.25--detections--8--car--53.5--35x18--215.105v250.123",
    "percentage_probability": 53.49740982055664,
    "box_points": [
      215,
      105,
      250,
      123
    ]
  }
}
