{
  "id": "731-679-N--2020-05-05--13.25.10--detections",
  "model": "ResNet50_COCO_best_v2.0.1.h5",
  "summary": {
    "total": 5,
    "car": 3,
    "bus": 2
  },
  "731-679-N--2020-05-05--13.25.10--detections--1--car--83.3--25x11--231.100v256.111": {
    "type": "car",
    "id": "731-679-N--2020-05-05--13.25.10--detections--1--car--83.3--25x11--231.100v256.111",
    "percentage_probability": 83.33548307418823,
    "box_points": [
      231,
      100,
      256,
      111
    ]
  },
  "731-679-N--2020-05-05--13.25.10--detections--2--car--42.5--17x16--334.56v351.72": {
    "type": "car",
    "id": "731-679-N--2020-05-05--13.25.10--detections--2--car--42.5--17x16--334.56v351.72",
    "percentage_probability": 42.488229274749756,
    "box_points": [
      334,
      56,
      351,
      72
    ]
  },
  "731-679-N--2020-05-05--13.25.10--detections--3--bus--67.5--31x33--59.128v90.161": {
    "type": "bus",
    "id": "731-679-N--2020-05-05--13.25.10--detections--3--bus--67.5--31x33--59.128v90.161",
    "percentage_probability": 67.5302505493164,
    "box_points": [
      59,
      128,
      90,
      161
    ]
  },
  "731-679-N--2020-05-05--13.25.10--detections--4--car--28.8--58x57--82.163v140.220": {
    "type": "car",
    "id": "731-679-N--2020-05-05--13.25.10--detections--4--car--28.8--58x57--82.163v140.220",
    "percentage_probability": 28.79253625869751,
    "box_points": [
      82,
      163,
      140,
      220
    ]
  },
  "731-679-N--2020-05-05--13.25.10--detections--5--bus--46.2--58x61--82.161v140.222": {
    "type": "bus",
    "id": "731-679-N--2020-05-05--13.25.10--detections--5--bus--46.2--58x61--82.161v140.222",
    "percentage_probability": 46.24972641468048,
    "box_points": [
      82,
      161,
      140,
      222
    ]
  }
}
