{
  "id": "731-679-N--2020-05-05--13.43.00--detections",
  "model": "ResNet50_COCO_best_v2.0.1.h5",
  "summary": {
    "total": 7,
    "car": 6,
    "bus": 1
  },
  "731-679-N--2020-05-05--13.43.00--detections--1--car--57.9--16x12--91.88v107.100": {
    "type": "car",
    "id": "731-679-N--2020-05-05--13.43.00--detections--1--car--57.9--16x12--91.88v107.100",
    "percentage_probability": 57.8599214553833,
    "box_points": [
      91,
      88,
      107,
      100
    ]
  },
  "731-679-N--2020-05-05--13.43.00--detections--2--car--30.8--23x16--328.57v351.73": {
    "type": "car",
    "id": "731-679-N--2020-05-05--13.43.00--detections--2--car--30.8--23x16--328.57v351.73",
    "percentage_probability": 30.75765371322632,
    "box_points": [
      328,
      57,
      351,
      73
    ]
  },
  "731-679-N--2020-05-05--13.43.00--detections--3--car--65.2--19x12--125.93v144.105": {
    "type": "car",
    "id": "731-679-N--2020-05-05--13.43.00--detections--3--car--65.2--19x12--125.93v144.105",
    "percentage_probability": 65.17555713653564,
    "box_points": [
      125,
      93,
      144,
      105
    ]
  },
  "731-679-N--2020-05-05--13.43.00--detections--4--car--50.7--24x17--110.106v134.123": {
    "type": "car",
    "id": "731-679-N--2020-05-05--13.43.00--detections--4--car--50.7--24x17--110.106v134.123",
    "percentage_probability": 50.732702016830444,
    "box_points": [
      110,
      106,
      134,
      123
    ]
  },
  "731-679-N--2020-05-05--13.43.00--detections--5--car--92.0--59x38--229.138v288.176": {
    "type": "car",
    "id": "731-679-N--2020-05-05--13.43.00--detections--5--car--92.0--59x38--229.138v288.176",
    "percentage_probability": 92.005056142807,
    "box_points": [
      229,
      138,
      288,
      176
    ]
  },
  "731-679-N--2020-05-05--13.43.00--detections--6--car--57.5--57x54--87.172v144.226": {
    "type": "car",
    "id": "731-679-N--2020-05-05--13.43.00--detections--6--car--57.5--57x54--87.172v144.226",
    "percentage_probability": 57.54597783088684,
    "box_points": [
      87,
      172,
      144,
      226
    ]
  },
  "731-679-N--2020-05-05--13.43.00--detections--7--bus--47.8--56x53--87.173v143.226": {
    "type": "bus",
    "id": "731-679-N--2020-05-05--13.43.00--detections--7--bus--47.8--56x53--87.173v143.226",
    "percentage_probability": 47.80516028404236,
    "box_points": [
      87,
      173,
      143,
      226
    ]
  }
}
