{
  "id": "731-679-N--2020-05-05--13.16.51--detections",
  "model": "ResNet50_COCO_best_v2.0.1.h5",
  "summary": {
    "total": 7,
    "car": 7
  },
  "731-679-N--2020-05-05--13.16.51--detections--1--car--46.8--10x8--91.82v101.90": {
    "type": "car",
    "id": "731-679-N--2020-05-05--13.16.51--detections--1--car--46.8--10x8--91.82v101.90",
    "percentage_probability": 46.78370654582977,
    "box_points": [
      91,
      82,
      101,
      90
    ]
  },
  "731-679-N--2020-05-05--13.16.51--detections--2--car--45.5--14x10--109.89v123.99": {
    "type": "car",
    "id": "731-679-N--2020-05-05--13.16.51--detections--2--car--45.5--14x10--109.89v123.99",
    "percentage_probability": 45.47434747219086,
    "box_points": [
      109,
      89,
      123,
      99
    ]
  },
  "731-679-N--2020-05-05--13.16.51--detections--3--car--69.8--39x18--260.109v299.127": {
    "type": "car",
    "id": "731-679-N--2020-05-05--13.16.51--detections--3--car--69.8--39x18--260.109v299.127",
    "percentage_probability": 69.81796026229858,
    "box_points": [
      260,
      109,
      299,
      127
    ]
  },
  "731-679-N--2020-05-05--13.16.51--detections--4--car--45.9--24x25--53.117v77.142": {
    "type": "car",
    "id": "731-679-N--2020-05-05--13.16.51--detections--4--car--45.9--24x25--53.117v77.142",
    "percentage_probability": 45.86409330368042,
    "box_points": [
      53,
      117,
      77,
      142
    ]
  },
  "731-679-N--2020-05-05--13.16.51--detections--5--car--39.4--28x25--56.125v84.150": {
    "type": "car",
    "id": "731-679-N--2020-05-05--13.16.51--detections--5--car--39.4--28x25--56.125v84.150",
    "percentage_probability": 39.42132294178009,
    "box_points": [
      56,
      125,
      84,
      150
    ]
  },
  "731-679-N--2020-05-05--13.16.51--detections--6--car--56.8--30x29--60.130v90.159": {
    "type": "car",
    "id": "731-679-N--2020-05-05--13.16.51--detections--6--car--56.8--30x29--60.130v90.159",
    "percentage_probability": 56.79957866668701,
    "box_points": [
      60,
      130,
      90,
      159
    ]
  },
  "731-679-N--2020-05-05--13.16.51--detections--7--car--85.5--42x47--70.153v112.200": {
    "type": "car",
    "id": "731-679-N--2020-05-05--13.16.51--detections--7--car--85.5--42x47--70.153v112.200",
    "percentage_probability": 85.54884195327759,
    "box_points": [
      70,
      153,
      112,
      200
    ]
  }
}
