{
  "id": "731-679-N--2020-05-05--13.26.57--detections",
  "model": "ResNet50_COCO_best_v2.0.1.h5",
  "summary": {
    "total": 12,
    "car": 11,
    "bus": 1
  },
  "731-679-N--2020-05-05--13.26.57--detections--1--car--25.3--11x8--90.82v101.90": {
    "type": "car",
    "id": "731-679-N--2020-05-05--13.26.57--detections--1--car--25.3--11x8--90.82v101.90",
    "percentage_probability": 25.326097011566162,
    "box_points": [
      90,
      82,
      101,
      90
    ]
  },
  "731-679-N--2020-05-05--13.26.57--detections--2--car--47.9--20x14--109.94v129.108": {
    "type": "car",
    "id": "731-679-N--2020-05-05--13.26.57--detections--2--car--47.9--20x14--109.94v129.108",
    "percentage_probability": 47.85089194774628,
    "box_points": [
      109,
      94,
      129,
      108
    ]
  },
  "731-679-N--2020-05-05--13.26.57--detections--3--bus--29.5--16x11--38.102v54.113": {
    "type": "bus",
    "id": "731-679-N--2020-05-05--13.26.57--detections--3--bus--29.5--16x11--38.102v54.113",
    "percentage_probability": 29.46363091468811,
    "box_points": [
      38,
      102,
      54,
      113
    ]
  },
  "731-679-N--2020-05-05--13.26.57--detections--4--car--47.1--19x18--45.109v64.127": {
    "type": "car",
    "id": "731-679-N--2020-05-05--13.26.57--detections--4--car--47.1--19x18--45.109v64.127",
    "percentage_probability": 47.10628390312195,
    "box_points": [
      45,
      109,
      64,
      127
    ]
  },
  "731-679-N--2020-05-05--13.26.57--detections--5--car--25.7--17x16--334.56v351.72": {
    "type": "car",
    "id": "731-679-N--2020-05-05--13.26.57--detections--5--car--25.7--17x16--334.56v351.72",
    "percentage_probability": 25.671780109405518,
    "box_points": [
      334,
      56,
      351,
      72
    ]
  },
  "731-679-N--2020-05-05--13.26.57--detections--6--car--62.5--19x13--97.102v116.115": {
    "type": "car",
    "id": "731-679-N--2020-05-05--13.26.57--detections--6--car--62.5--19x13--97.102v116.115",
    "percentage_probability": 62.51033544540405,
    "box_points": [
      97,
      102,
      116,
      115
    ]
  },
  "731-679-N--2020-05-05--13.26.57--detections--7--car--27.0--22x19--48.114v70.133": {
    "type": "car",
    "id": "731-679-N--2020-05-05--13.26.57--detections--7--car--27.0--22x19--48.114v70.133",
    "percentage_probability": 27.02731490135193,
    "box_points": [
      48,
      114,
      70,
      133
    ]
  },
  "731-679-N--2020-05-05--13.26.57--detections--8--car--54.7--21x19--53.119v74.138": {
    "type": "car",
    "id": "731-679-N--2020-05-05--13.26.57--detections--8--car--54.7--21x19--53.119v74.138",
    "percentage_probability": 54.7180712223053,
    "box_points": [
      53,
      119,
      74,
      138
    ]
  },
  "731-679-N--2020-05-05--13.26.57--detections--9--car--54.7--31x25--62.137v93.162": {
    "type": "car",
    "id": "731-679-N--2020-05-05--13.26.57--detections--9--car--54.7--31x25--62.137v93.162",
    "percentage_probability": 54.68960404396057,
    "box_points": [
      62,
      137,
      93,
      162
    ]
  },
  "731-679-N--2020-05-05--13.26.57--detections--10--car--96.6--58x30--210.135v268.165": {
    "type": "car",
    "id": "731-679-N--2020-05-05--13.26.57--detections--10--car--96.6--58x30--210.135v268.165",
    "percentage_probability": 96.55771255493164,
    "box_points": [
      210,
      135,
      268,
      165
    ]
  },
  "731-679-N--2020-05-05--13.26.57--detections--11--car--82.7--43x44--75.151v118.195": {
    "type": "car",
    "id": "731-679-N--2020-05-05--13.26.57--detections--11--car--82.7--43x44--75.151v118.195",
    "percentage_probability": 82.72180557250977,
    "box_points": [
      75,
      151,
      118,
      195
    ]
  },
  "731-679-N--2020-05-05--13.26.57--detections--12--car--78.6--74x47--107.191v181.238": {
    "type": "car",
    "id": "731-679-N--2020-05-05--13.26.57--detections--12--car--78.6--74x47--107.191v181.238",
    "percentage_probability": 78.63343358039856,
    "box_points": [
      107,
      191,
      181,
      238
    ]
  }
}
