{
  "id": "731-679-N--2020-05-05--13.26.36--detections",
  "model": "ResNet50_COCO_best_v2.0.1.h5",
  "summary": {
    "total": 6,
    "car": 5,
    "bus": 1
  },
  "731-679-N--2020-05-05--13.26.36--detections--1--car--48.9--11x9--69.79v80.88": {
    "type": "car",
    "id": "731-679-N--2020-05-05--13.26.36--detections--1--car--48.9--11x9--69.79v80.88",
    "percentage_probability": 48.87876808643341,
    "box_points": [
      69,
      79,
      80,
      88
    ]
  },
  "731-679-N--2020-05-05--13.26.36--detections--2--car--25.7--9x8--29.85v38.93": {
    "type": "car",
    "id": "731-679-N--2020-05-05--13.26.36--detections--2--car--25.7--9x8--29.85v38.93",
    "percentage_probability": 25.669434666633606,
    "box_points": [
      29,
      85,
      38,
      93
    ]
  },
  "731-679-N--2020-05-05--13.26.36--detections--3--car--58.3--12x10--33.90v45.100": {
    "type": "car",
    "id": "731-679-N--2020-05-05--13.26.36--detections--3--car--58.3--12x10--33.90v45.100",
    "percentage_probability": 58.30239653587341,
    "box_points": [
      33,
      90,
      45,
      100
    ]
  },
  "731-679-N--2020-05-05--13.26.36--detections--4--car--56.0--21x17--330.56v351.73": {
    "type": "car",
    "id": "731-679-N--2020-05-05--13.26.36--detections--4--car--56.0--21x17--330.56v351.73",
    "percentage_probability": 55.98604083061218,
    "box_points": [
      330,
      56,
      351,
      73
    ]
  },
  "731-679-N--2020-05-05--13.26.36--detections--5--car--62.6--72x51--106.187v178.238": {
    "type": "car",
    "id": "731-679-N--2020-05-05--13.26.36--detections--5--car--62.6--72x51--106.187v178.238",
    "percentage_probability": 62.61056661605835,
    "box_points": [
      106,
      187,
      178,
      238
    ]
  },
  "731-679-N--2020-05-05--13.26.36--detections--6--bus--54.2--72x51--106.187v178.238": {
    "type": "bus",
    "id": "731-679-N--2020-05-05--13.26.36--detections--6--bus--54.2--72x51--106.187v178.238",
    "percentage_probability": 54.2222261428833,
    "box_points": [
      106,
      187,
      178,
      238
    ]
  }
}
