{
  "id": "731-679-N--2020-05-05--13.53.55--detections",
  "model": "ResNet50_COCO_best_v2.0.1.h5",
  "summary": {
    "total": 9,
    "car": 7,
    "bus": 2
  },
  "731-679-N--2020-05-05--13.53.55--detections--1--car--40.1--9x8--76.77v85.85": {
    "type": "car",
    "id": "731-679-N--2020-05-05--13.53.55--detections--1--car--40.1--9x8--76.77v85.85",
    "percentage_probability": 40.069958567619324,
    "box_points": [
      76,
      77,
      85,
      85
    ]
  },
  "731-679-N--2020-05-05--13.53.55--detections--2--car--32.6--16x14--206.73v222.87": {
    "type": "car",
    "id": "731-679-N--2020-05-05--13.53.55--detections--2--car--32.6--16x14--206.73v222.87",
    "percentage_probability": 32.55060613155365,
    "box_points": [
      206,
      73,
      222,
      87
    ]
  },
  "731-679-N--2020-05-05--13.53.55--detections--3--car--49.2--15x16--41.98v56.114": {
    "type": "car",
    "id": "731-679-N--2020-05-05--13.53.55--detections--3--car--49.2--15x16--41.98v56.114",
    "percentage_probability": 49.16483461856842,
    "box_points": [
      41,
      98,
      56,
      114
    ]
  },
  "731-679-N--2020-05-05--13.53.55--detections--4--car--26.7--19x15--142.80v161.95": {
    "type": "car",
    "id": "731-679-N--2020-05-05--13.53.55--detections--4--car--26.7--19x15--142.80v161.95",
    "percentage_probability": 26.66270136833191,
    "box_points": [
      142,
      80,
      161,
      95
    ]
  },
  "731-679-N--2020-05-05--13.53.55--detections--5--bus--42.4--15x17--27.80v42.97": {
    "type": "bus",
    "id": "731-679-N--2020-05-05--13.53.55--detections--5--bus--42.4--15x17--27.80v42.97",
    "percentage_probability": 42.40005016326904,
    "box_points": [
      27,
      80,
      42,
      97
    ]
  },
  "731-679-N--2020-05-05--13.53.55--detections--6--car--79.2--29x14--211.100v240.114": {
    "type": "car",
    "id": "731-679-N--2020-05-05--13.53.55--detections--6--car--79.2--29x14--211.100v240.114",
    "percentage_probability": 79.21260595321655,
    "box_points": [
      211,
      100,
      240,
      114
    ]
  },
  "731-679-N--2020-05-05--13.53.55--detections--7--car--71.1--22x22--50.108v72.130": {
    "type": "car",
    "id": "731-679-N--2020-05-05--13.53.55--detections--7--car--71.1--22x22--50.108v72.130",
    "percentage_probability": 71.08762264251709,
    "box_points": [
      50,
      108,
      72,
      130
    ]
  },
  "731-679-N--2020-05-05--13.53.55--detections--8--bus--26.5--21x21--50.109v71.130": {
    "type": "bus",
    "id": "731-679-N--2020-05-05--13.53.55--detections--8--bus--26.5--21x21--50.109v71.130",
    "percentage_probability": 26.516467332839966,
    "box_points": [
      50,
      109,
      71,
      130
    ]
  },
  "731-679-N--2020-05-05--13.53.55--detections--9--car--69.2--51x46--81.172v132.218": {
    "type": "car",
    "id": "731-679-N--2020-05-05--13.53.55--detections--9--car--69.2--51x46--81.172v132.218",
    "percentage_probability": 69.21021938323975,
    "box_points": [
      81,
      172,
      132,
      218
    ]
  }
}
