{
  "id": "731-679-N--2020-05-05--13.29.04--detections",
  "model": "ResNet50_COCO_best_v2.0.1.h5",
  "summary": {
    "total": 6,
    "car": 6
  },
  "731-679-N--2020-05-05--13.29.04--detections--1--car--26.1--8x7--28.81v36.88": {
    "type": "car",
    "id": "731-679-N--2020-05-05--13.29.04--detections--1--car--26.1--8x7--28.81v36.88",
    "percentage_probability": 26.14414095878601,
    "box_points": [
      28,
      81,
      36,
      88
    ]
  },
  "731-679-N--2020-05-05--13.29.04--detections--2--car--41.6--20x16--331.56v351.72": {
    "type": "car",
    "id": "731-679-N--2020-05-05--13.29.04--detections--2--car--41.6--20x16--331.56v351.72",
    "percentage_probability": 41.61476492881775,
    "box_points": [
      331,
      56,
      351,
      72
    ]
  },
  "731-679-N--2020-05-05--13.29.04--detections--3--car--86.1--41x16--267.112v308.128": {
    "type": "car",
    "id": "731-679-N--2020-05-05--13.29.04--detections--3--car--86.1--41x16--267.112v308.128",
    "percentage_probability": 86.13913655281067,
    "box_points": [
      267,
      112,
      308,
      128
    ]
  },
  "731-679-N--2020-05-05--13.29.04--detections--4--car--95.9--48x28--186.124v234.152": {
    "type": "car",
    "id": "731-679-N--2020-05-05--13.29.04--detections--4--car--95.9--48x28--186.124v234.152",
    "percentage_probability": 95.9426999092102,
    "box_points": [
      186,
      124,
      234,
      152
    ]
  },
  "731-679-N--2020-05-05--13.29.04--detections--5--car--92.7--55x52--83.165v138.217": {
    "type": "car",
    "id": "731-679-N--2020-05-05--13.29.04--detections--5--car--92.7--55x52--83.165v138.217",
    "percentage_probability": 92.71384477615356,
    "box_points": [
      83,
      165,
      138,
      217
    ]
  },
  "731-679-N--2020-05-05--13.29.04--detections--6--car--95.4--72x51--222.160v294.211": {
    "type": "car",
    "id": "731-679-N--2020-05-05--13.29.04--detections--6--car--95.4--72x51--222.160v294.211",
    "percentage_probability": 95.43392062187195,
    "box_points": [
      222,
      160,
      294,
      211
    ]
  }
}
