{
  "id": "731-679-N--2020-05-05--13.22.57--detections",
  "model": "ResNet50_COCO_best_v2.0.1.h5",
  "summary": {
    "total": 5,
    "car": 5
  },
  "731-679-N--2020-05-05--13.22.57--detections--1--car--41.9--12x8--105.79v117.87": {
    "type": "car",
    "id": "731-679-N--2020-05-05--13.22.57--detections--1--car--41.9--12x8--105.79v117.87",
    "percentage_probability": 41.868042945861816,
    "box_points": [
      105,
      79,
      117,
      87
    ]
  },
  "731-679-N--2020-05-05--13.22.57--detections--2--car--25.4--18x17--333.56v351.73": {
    "type": "car",
    "id": "731-679-N--2020-05-05--13.22.57--detections--2--car--25.4--18x17--333.56v351.73",
    "percentage_probability": 25.43213665485382,
    "box_points": [
      333,
      56,
      351,
      73
    ]
  },
  "731-679-N--2020-05-05--13.22.57--detections--3--car--75.7--16x14--89.83v105.97": {
    "type": "car",
    "id": "731-679-N--2020-05-05--13.22.57--detections--3--car--75.7--16x14--89.83v105.97",
    "percentage_probability": 75.66614151000977,
    "box_points": [
      89,
      83,
      105,
      97
    ]
  },
  "731-679-N--2020-05-05--13.22.57--detections--4--car--84.9--17x15--334.128v351.143": {
    "type": "car",
    "id": "731-679-N--2020-05-05--13.22.57--detections--4--car--84.9--17x15--334.128v351.143",
    "percentage_probability": 84.94253158569336,
    "box_points": [
      334,
      128,
      351,
      143
    ]
  },
  "731-679-N--2020-05-05--13.22.57--detections--5--car--68.9--45x48--80.157v125.205": {
    "type": "car",
    "id": "731-679-N--2020-05-05--13.22.57--detections--5--car--68.9--45x48--80.157v125.205",
    "percentage_probability": 68.92516016960144,
    "box_points": [
      80,
      157,
      125,
      205
    ]
  }
}
