{
  "id": "731-679-N--2020-05-05--13.27.07--detections",
  "model": "ResNet50_COCO_best_v2.0.1.h5",
  "summary": {
    "total": 20,
    "car": 19,
    "bus": 1
  },
  "731-679-N--2020-05-05--13.27.07--detections--1--car--31.0--10x7--101.77v111.84": {
    "type": "car",
    "id": "731-679-N--2020-05-05--13.27.07--detections--1--car--31.0--10x7--101.77v111.84",
    "percentage_probability": 31.031233072280884,
    "box_points": [
      101,
      77,
      111,
      84
    ]
  },
  "731-679-N--2020-05-05--13.27.07--detections--2--car--28.9--9x7--111.76v120.83": {
    "type": "car",
    "id": "731-679-N--2020-05-05--13.27.07--detections--2--car--28.9--9x7--111.76v120.83",
    "percentage_probability": 28.87556254863739,
    "box_points": [
      111,
      76,
      120,
      83
    ]
  },
  "731-679-N--2020-05-05--13.27.07--detections--3--car--34.1--9x7--64.79v73.86": {
    "type": "car",
    "id": "731-679-N--2020-05-05--13.27.07--detections--3--car--34.1--9x7--64.79v73.86",
    "percentage_probability": 34.09872353076935,
    "box_points": [
      64,
      79,
      73,
      86
    ]
  },
  "731-679-N--2020-05-05--13.27.07--detections--4--car--31.9--9x8--81.78v90.86": {
    "type": "car",
    "id": "731-679-N--2020-05-05--13.27.07--detections--4--car--31.9--9x8--81.78v90.86",
    "percentage_probability": 31.852728128433228,
    "box_points": [
      81,
      78,
      90,
      86
    ]
  },
  "731-679-N--2020-05-05--13.27.07--detections--5--car--33.1--14x7--32.92v46.99": {
    "type": "car",
    "id": "731-679-N--2020-05-05--13.27.07--detections--5--car--33.1--14x7--32.92v46.99",
    "percentage_probability": 33.109307289123535,
    "box_points": [
      32,
      92,
      46,
      99
    ]
  },
  "731-679-N--2020-05-05--13.27.07--detections--6--car--27.2--18x11--167.89v185.100": {
    "type": "car",
    "id": "731-679-N--2020-05-05--13.27.07--detections--6--car--27.2--18x11--167.89v185.100",
    "percentage_probability": 27.189934253692627,
    "box_points": [
      167,
      89,
      185,
      100
    ]
  },
  "731-679-N--2020-05-05--13.27.07--detections--7--car--55.6--16x12--33.93v49.105": {
    "type": "car",
    "id": "731-679-N--2020-05-05--13.27.07--detections--7--car--55.6--16x12--33.93v49.105",
    "percentage_probability": 55.556970834732056,
    "box_points": [
      33,
      93,
      49,
      105
    ]
  },
  "731-679-N--2020-05-05--13.27.07--detections--8--car--32.1--10x9--48.95v58.104": {
    "type": "car",
    "id": "731-679-N--2020-05-05--13.27.07--detections--8--car--32.1--10x9--48.95v58.104",
    "percentage_probability": 32.08438754081726,
    "box_points": [
      48,
      95,
      58,
      104
    ]
  },
  "731-679-N--2020-05-05--13.27.07--detections--9--car--40.3--16x15--37.97v53.112": {
    "type": "car",
    "id": "731-679-N--2020-05-05--13.27.07--detections--9--car--40.3--16x15--37.97v53.112",
    "percentage_probability": 40.25368690490723,
    "box_points": [
      37,
      97,
      53,
      112
    ]
  },
  "731-679-N--2020-05-05--13.27.07--detections--10--car--27.6--17x11--39.103v56.114": {
    "type": "car",
    "id": "731-679-N--2020-05-05--13.27.07--detections--10--car--27.6--17x11--39.103v56.114",
    "percentage_probability": 27.566683292388916,
    "box_points": [
      39,
      103,
      56,
      114
    ]
  },
  "731-679-N--2020-05-05--13.27.07--detections--11--car--29.5--22x15--54.128v76.143": {
    "type": "car",
    "id": "731-679-N--2020-05-05--13.27.07--detections--11--car--29.5--22x15--54.128v76.143",
    "percentage_probability": 29.497188329696655,
    "box_points": [
      54,
      128,
      76,
      143
    ]
  },
  "731-679-N--2020-05-05--13.27.07--detections--12--car--42.6--22x18--329.55v351.73": {
    "type": "car",
    "id": "731-679-N--2020-05-05--13.27.07--detections--12--car--42.6--22x18--329.55v351.73",
    "percentage_probability": 42.602819204330444,
    "box_points": [
      329,
      55,
      351,
      73
    ]
  },
  "731-679-N--2020-05-05--13.27.07--detections--13--car--76.8--20x15--122.89v142.104": {
    "type": "car",
    "id": "731-679-N--2020-05-05--13.27.07--detections--13--car--76.8--20x15--122.89v142.104",
    "percentage_probability": 76.84574127197266,
    "box_points": [
      122,
      89,
      142,
      104
    ]
  },
  "731-679-N--2020-05-05--13.27.07--detections--14--car--59.1--20x18--44.108v64.126": {
    "type": "car",
    "id": "731-679-N--2020-05-05--13.27.07--detections--14--car--59.1--20x18--44.108v64.126",
    "percentage_probability": 59.07606482505798,
    "box_points": [
      44,
      108,
      64,
      126
    ]
  },
  "731-679-N--2020-05-05--13.27.07--detections--15--car--56.3--22x20--53.119v75.139": {
    "type": "car",
    "id": "731-679-N--2020-05-05--13.27.07--detections--15--car--56.3--22x20--53.119v75.139",
    "percentage_probability": 56.2680184841156,
    "box_points": [
      53,
      119,
      75,
      139
    ]
  },
  "731-679-N--2020-05-05--13.27.07--detections--16--car--65.0--38x18--288.119v326.137": {
    "type": "car",
    "id": "731-679-N--2020-05-05--13.27.07--detections--16--car--65.0--38x18--288.119v326.137",
    "percentage_probability": 65.04600048065186,
    "box_points": [
      288,
      119,
      326,
      137
    ]
  },
  "731-679-N--2020-05-05--13.27.07--detections--17--car--50.9--30x25--61.137v91.162": {
    "type": "car",
    "id": "731-679-N--2020-05-05--13.27.07--detections--17--car--50.9--30x25--61.137v91.162",
    "percentage_probability": 50.8630633354187,
    "box_points": [
      61,
      137,
      91,
      162
    ]
  },
  "731-679-N--2020-05-05--13.27.07--detections--18--car--68.1--43x43--74.152v117.195": {
    "type": "car",
    "id": "731-679-N--2020-05-05--13.27.07--detections--18--car--68.1--43x43--74.152v117.195",
    "percentage_probability": 68.05973649024963,
    "box_points": [
      74,
      152,
      117,
      195
    ]
  },
  "731-679-N--2020-05-05--13.27.07--detections--19--car--62.7--74x47--107.191v181.238": {
    "type": "car",
    "id": "731-679-N--2020-05-05--13.27.07--detections--19--car--62.7--74x47--107.191v181.238",
    "percentage_probability": 62.73050308227539,
    "box_points": [
      107,
      191,
      181,
      238
    ]
  },
  "731-679-N--2020-05-05--13.27.07--detections--20--bus--29.5--73x47--114.191v187.238": {
    "type": "bus",
    "id": "731-679-N--2020-05-05--13.27.07--detections--20--bus--29.5--73x47--114.191v187.238",
    "percentage_probability": 29.50073480606079,
    "box_points": [
      114,
      191,
      187,
      238
    ]
  }
}
